newmap/__init__.py
newmap/_c_newmap_count_kmers.abi3.so
newmap/_c_newmap_generate_index.abi3.so
newmap/fasta.py
newmap/index.py
newmap/main.py
newmap/search.py
newmap/track.py
newmap/util.py
newmap.libs/libgomp-a34b3233.so.1.0.0
newmap-0.2.dist-info/METADATA
newmap-0.2.dist-info/WHEEL
newmap-0.2.dist-info/entry_points.txt
newmap-0.2.dist-info/top_level.txt
newmap-0.2.dist-info/RECORD
newmap-0.2.dist-info/licenses/LICENSE
