Metadata-Version: 2.4
Name: newmap
Version: 0.2
Summary: Newmap: tools for genome and methylome mappability
Author-email: Eric Roberts <eric.roberts@uhn.ca>, Michael Hoffman <michael.hoffman@utoronto.ca>
License-Expression: GPL-3.0-only
Project-URL: Bug Tracker, https://github.com/hoffmangroup/newmap/issues
Project-URL: Download, https://pypi.python.org/pypi/newmap
Project-URL: Homepage, https://hoffmanlab.org/proj/newmap
Classifier: Natural Language :: English
Classifier: Development Status :: 5 - Production/Stable
Classifier: Intended Audience :: Science/Research
Classifier: Operating System :: Unix
Classifier: Topic :: Scientific/Engineering :: Bio-Informatics
Classifier: Programming Language :: Python :: 3
Requires-Python: >=3.9
License-File: LICENSE
Requires-Dist: numpy
Dynamic: license-file
